developerpubsubsdk/__init__.py
developerpubsubsdk/abstractClientSDK.py
developerpubsubsdk/api/__init__.py
developerpubsubsdk/bean/PublishProtos_pb2.py
developerpubsubsdk/bean/SubscripProtos_pb2.py
developerpubsubsdk/bean/__init__.py
developerpubsubsdk/bean/handler/__init__.py
developerpubsubsdk/bean/handler/subClientHandler.py
developerpubsubsdk/src/__init__.py
developerpubsubsdk/src/config.py
developerpubsubsdk/src/httpResult.py
developer_pub_sub_sdk-2.1.dist-info/METADATA
developer_pub_sub_sdk-2.1.dist-info/WHEEL
developer_pub_sub_sdk-2.1.dist-info/top_level.txt
developer_pub_sub_sdk-2.1.dist-info/RECORD
