Metadata-Version: 2.1
Name: developer-pub-sub-sdk
Version: 2.1
Summary: 为开发者的sdk
Home-page: UNKNOWN
Author: jiltfly
Author-email: it.shuaifei@gmail.com
Maintainer: jiltfly
Maintainer-email: t-jishuaifei@irootech.com
License: BSD License
Platform: all
Classifier: Development Status :: 4 - Beta
Classifier: Operating System :: OS Independent
Classifier: Intended Audience :: Developers
Classifier: License :: OSI Approved :: BSD License
Classifier: Programming Language :: Python
Classifier: Programming Language :: Python :: Implementation
Classifier: Programming Language :: Python :: 2
Classifier: Programming Language :: Python :: 2.7
Classifier: Programming Language :: Python :: 3
Classifier: Programming Language :: Python :: 3.4
Classifier: Programming Language :: Python :: 3.5
Classifier: Programming Language :: Python :: 3.6
Classifier: Topic :: Software Development :: Libraries
Requires-Dist: requests (>=2.20.1)
Requires-Dist: six (>=1.11.0)
Requires-Dist: protobuf (>=3.6.0)
